ZetcodeJavascriptJiaochengChuyi/README.md
ZetcodeJavascriptJiaochengChuyi/__init__.py
ZetcodeJavascriptJiaochengChuyi/__main__.py
ZetcodeJavascriptJiaochengChuyi/file.epub
ZetcodeJavascriptJiaochengChuyi/index.html
ZetcodeJavascriptJiaochengChuyi/css/__init__.py
ZetcodeJavascriptJiaochengChuyi/css/annotations.css
ZetcodeJavascriptJiaochengChuyi/css/main.css
ZetcodeJavascriptJiaochengChuyi/css/normalize.css
ZetcodeJavascriptJiaochengChuyi/css/popup.css
ZetcodeJavascriptJiaochengChuyi/font/__init__.py
ZetcodeJavascriptJiaochengChuyi/font/fontello.eot
ZetcodeJavascriptJiaochengChuyi/font/fontello.svg
ZetcodeJavascriptJiaochengChuyi/font/fontello.ttf
ZetcodeJavascriptJiaochengChuyi/font/fontello.woff
ZetcodeJavascriptJiaochengChuyi/img/__init__.py
ZetcodeJavascriptJiaochengChuyi/img/annotator-glyph-sprite.png
ZetcodeJavascriptJiaochengChuyi/img/annotator-icon-sprite.png
ZetcodeJavascriptJiaochengChuyi/img/apple-touch-icon.png
ZetcodeJavascriptJiaochengChuyi/img/cancelfullscreen.png
ZetcodeJavascriptJiaochengChuyi/img/close.png
ZetcodeJavascriptJiaochengChuyi/img/fullscreen.png
ZetcodeJavascriptJiaochengChuyi/img/loader.gif
ZetcodeJavascriptJiaochengChuyi/img/menu-icon.png
ZetcodeJavascriptJiaochengChuyi/img/save.png
ZetcodeJavascriptJiaochengChuyi/img/saved.png
ZetcodeJavascriptJiaochengChuyi/img/settings-s.png
ZetcodeJavascriptJiaochengChuyi/img/settings.png
ZetcodeJavascriptJiaochengChuyi/img/star.png
ZetcodeJavascriptJiaochengChuyi/js/__init__.py
ZetcodeJavascriptJiaochengChuyi/js/epub.js
ZetcodeJavascriptJiaochengChuyi/js/epub.min.js
ZetcodeJavascriptJiaochengChuyi/js/epub.min.map
ZetcodeJavascriptJiaochengChuyi/js/hooks.min.js
ZetcodeJavascriptJiaochengChuyi/js/hooks.min.map
ZetcodeJavascriptJiaochengChuyi/js/reader.js
ZetcodeJavascriptJiaochengChuyi/js/reader.js.map
ZetcodeJavascriptJiaochengChuyi/js/reader.min.js
ZetcodeJavascriptJiaochengChuyi/js/reader.min.map
ZetcodeJavascriptJiaochengChuyi/js/hooks/__init__.py
zetcode_javascript_jiaocheng_chuyi-2024.3.5.0.dist-info/METADATA
zetcode_javascript_jiaocheng_chuyi-2024.3.5.0.dist-info/WHEEL
zetcode_javascript_jiaocheng_chuyi-2024.3.5.0.dist-info/entry_points.txt
zetcode_javascript_jiaocheng_chuyi-2024.3.5.0.dist-info/top_level.txt
zetcode_javascript_jiaocheng_chuyi-2024.3.5.0.dist-info/RECORD
